{
  "sections": {
    "main": {
      "type": "main-page",
      "disabled": true,
      "settings": {
        "padding_top": 28,
        "padding_bottom": 28
      }
    },
    "e0371858-bac0-413e-8d79-d69217a3561d": {
      "type": "image-banner-wave",
      "blocks": {
        "template--19108853809447__e0371858-bac0-413e-8d79-d69217a3561d-16861343725c909b26-0": {
          "type": "heading",
          "settings": {
            "heading": "LES CAPSULES D'ACTIF",
            "heading_size": "h0"
          }
        },
        "template--19108853809447__e0371858-bac0-413e-8d79-d69217a3561d-16861343725c909b26-1": {
          "type": "text",
          "settings": {
            "text": "<p>Texte capsules \/ innovation <\/p>",
            "text_style": "body"
          }
        }
      },
      "block_order": [
        "template--19108853809447__e0371858-bac0-413e-8d79-d69217a3561d-16861343725c909b26-0",
        "template--19108853809447__e0371858-bac0-413e-8d79-d69217a3561d-16861343725c909b26-1"
      ],
      "settings": {
        "image": "shopify:\/\/shop_images\/Hilo-cosmetiques-capsules-actifs-naturels_cfccb8e3-01c5-468f-a30f-ea1baa82f637.jpg",
        "svg-wave": "vague-blanche",
        "image_overlay_opacity": 0,
        "image_height": "medium",
        "adapt_height_first_image": false,
        "desktop_content_position": "top-center",
        "show_text_box": false,
        "desktop_content_alignment": "center",
        "color_scheme": "background-1",
        "mobile_content_alignment": "center",
        "stack_images_on_mobile": false,
        "show_text_below": false
      }
    },
    "00c32b12-4372-4263-9b83-5f1f40366b12": {
      "type": "image-with-text",
      "blocks": {
        "template--18276397875495__00c32b12-4372-4263-9b83-5f1f40366b12-1679427268d41d55f2-0": {
          "type": "heading",
          "settings": {
            "heading": "LEURS PROPRIÉTÉS",
            "heading_size": "h1"
          }
        },
        "template--18276397875495__00c32b12-4372-4263-9b83-5f1f40366b12-1679427268d41d55f2-1": {
          "type": "text",
          "settings": {
            "text": "<p>Nos actifs sont des huiles végétales <strong>100% naturelles<\/strong> reconnues pour des propriétés différentes. 🌱<\/p><p>Nous vous proposons 6 capsules d'actifs qui ont chacune des<strong> bienfaits spécifiques<\/strong> pour la peau. <\/p><p>Trois actifs sont à ajouter dans votre base de soin Hilo pour la rendre <strong>sur-mesure<\/strong>. ✨<\/p><p>Il y a donc plus de 50 combinaisons possibles, ce qui vous permettra d'obtenir un soin totalement <strong>adapté aux besoins de votre peau<\/strong> !<\/p>",
            "text_style": "body"
          }
        }
      },
      "block_order": [
        "template--18276397875495__00c32b12-4372-4263-9b83-5f1f40366b12-1679427268d41d55f2-0",
        "template--18276397875495__00c32b12-4372-4263-9b83-5f1f40366b12-1679427268d41d55f2-1"
      ],
      "custom_css": [
        "img {border-radius: 30px;}",
        "h2 {font-size: 30px !important; font-weight: bold !important ;}"
      ],
      "settings": {
        "customcss": "programme_text2 btn-circle",
        "eclat": "eclat-rose",
        "eclat_side": "gauche",
        "image": "shopify:\/\/shop_images\/capsules-actifs-creme-visage-naturelle_e5538163-1f76-48a5-901a-ff3e8273bd5d.jpg",
        "height": "adapt",
        "desktop_image_width": "small",
        "layout": "image_first",
        "desktop_content_position": "top",
        "desktop_content_alignment": "left",
        "content_layout": "no-overlap",
        "color_scheme": "background-1",
        "mobile_content_alignment": "left",
        "padding_top": 52,
        "padding_bottom": 52
      }
    },
    "multicolumns_reviews_CLdaeC": {
      "type": "multicolumns-reviews",
      "blocks": {
        "column_UBpPaT": {
          "type": "column",
          "settings": {
            "customcss": "",
            "image": "shopify:\/\/shop_images\/Hilo-cosmetiques-personnalises-capsule-onagre_d4fc6b24-a0ed-4553-939f-fd40400eb638.png",
            "title": "L'Onagre",
            "subtitle": "",
            "text": "<p><br\/>L’actif onagre est reconnue pour les propriétés suivantes :<br\/><br\/><\/p><p>✨<strong>Hydratant et adoucissant <\/strong>: il maintient l’hydratation naturelle de la peau et renforce son film hydrolipidique.<\/p><p>✨<strong>Revitalisant<\/strong> : il favorise la régénération de la peau tout en maintenant sa tonicité et son élasticité.<\/p><p>✨<strong>Antioxydant<\/strong> : il lutte contre les signes de l’âge, nourrit et répare la peau.<br\/><br\/><\/p><p>Il convient à <strong>tous les types de peau<\/strong> et est fortement recommandé pour les <strong>peaux déshydratées<\/strong>.<br\/><br\/><\/p><p>Composition : OENOTHERA BIENNIS (EVENING PRIMROSE) OIL, TOCOPHEROL, HELIANTHUS ANNUUS (SUNFLOWER) SEED OIL<\/p>",
            "link_label": "",
            "link": ""
          }
        },
        "column_9Xf7XR": {
          "type": "column",
          "settings": {
            "customcss": "",
            "title": "Column",
            "subtitle": "Column",
            "text": "<p>Pair text with an image to focus on your chosen product, collection, or blog post. Add details on availability, style, or even provide a review.<\/p>",
            "link_label": "",
            "link": ""
          }
        },
        "column_6QCigF": {
          "type": "column",
          "settings": {
            "customcss": "",
            "title": "Column",
            "subtitle": "Column",
            "text": "<p>Pair text with an image to focus on your chosen product, collection, or blog post. Add details on availability, style, or even provide a review.<\/p>",
            "link_label": "",
            "link": ""
          }
        }
      },
      "block_order": [
        "column_UBpPaT",
        "column_9Xf7XR",
        "column_6QCigF"
      ],
      "custom_css": [
        "img {align-items: center !important;}"
      ],
      "settings": {
        "customcss": "",
        "title": "Multicolumn",
        "subtitle": "",
        "heading_size": "h0",
        "image_width": "third",
        "image_ratio": "adapt",
        "columns_desktop": 2,
        "column_alignment": "left",
        "background_style": "none",
        "button_label": "Button label",
        "button_link": "",
        "color_scheme": "background-1",
        "columns_mobile": "1",
        "swipe_on_mobile": false,
        "padding_top": 36,
        "padding_bottom": 36
      }
    }
  },
  "order": [
    "main",
    "e0371858-bac0-413e-8d79-d69217a3561d",
    "00c32b12-4372-4263-9b83-5f1f40366b12",
    "multicolumns_reviews_CLdaeC"
  ]
}
